google_map_scraper/__init__.py
google_map_scraper/scraper.py
tests/__init__.py
tests/test_scraper.py
google_map_scraper-1.0.1.dist-info/LICENSE
google_map_scraper-1.0.1.dist-info/METADATA
google_map_scraper-1.0.1.dist-info/WHEEL
google_map_scraper-1.0.1.dist-info/top_level.txt
google_map_scraper-1.0.1.dist-info/RECORD
