Metadata-Version: 2.2
Name: google-map-scraper
Version: 1.0.1
Summary: A fast business scraper for Google Maps using Selenium
Home-page: https://github.com/mukhtar-ul-islam88/google_map_scraper
Author: Mukhtar ul Islam
Author-email: Mukhtarulislam88@hotmail.com
Classifier: Programming Language :: Python :: 3
Classifier: Operating System :: OS Independent
Classifier: License :: OSI Approved :: MIT License
Requires-Python: >=3.6
License-File: LICENSE
Requires-Dist: selenium==4.31.0
Requires-Dist: selenium-wire==5.1.0
Requires-Dist: webdriver-manager==4.0.2
Requires-Dist: blinker==1.7.0
Dynamic: author
Dynamic: author-email
Dynamic: classifier
Dynamic: description
Dynamic: description-content-type
Dynamic: home-page
Dynamic: requires-dist
Dynamic: requires-python
Dynamic: summary
